bwa_pe_tool/__init__.py
bwa_pe_tool/__main__.py
bwa_pe_tool/main.py
bwa_pe_tool/tools/__init__.py
bwa_pe_tool/tools/bwa_aln.py
bwa_pe_tool/tools/bwa_mem.py
bwa_pe_tool-0.3.dist-info/DESCRIPTION.rst
bwa_pe_tool-0.3.dist-info/METADATA
bwa_pe_tool-0.3.dist-info/RECORD
bwa_pe_tool-0.3.dist-info/WHEEL
bwa_pe_tool-0.3.dist-info/metadata.json
bwa_pe_tool-0.3.dist-info/top_level.txt
bwa_tool/__init__.py
bwa_tool/__main__.py
bwa_tool/main.py
bwa_tool/tools/__init__.py
bwa_tool/tools/bwa_aln.py
bwa_tool/tools/bwa_mem.py
